{
  "project_info": {
    "project_number": "348147721474",
    "firebase_url": "https://kuranfihristi-37d46.firebaseio.com",
    "project_id": "kuranfihristi-37d46",
    "storage_bucket": "kuranfihristi-37d46.appspot.com"
  },
  "client": [
    {
      "client_info": {
        "mobilesdk_app_id": "1:348147721474:android:9ee2061cab8ace38f90e1b",
        "android_client_info": {
          "package_name": "com.search.kuranfihristi"
        }
      },
      "oauth_client": [
        {
          "client_id": "348147721474-5vhe7m6ndrin2q65a2a1qev7om7fi4ei.apps.googleusercontent.com",
          "client_type": 1,
          "android_info": {
            "package_name": "com.search.kuranfihristi",
            "certificate_hash": "208574cf41a70cfc85d07076b91df2ef34961cbb"
          }
        },
        {
          "client_id": "348147721474-bu0htpm6ricu3d4dlunje7gmfidkdga3.apps.googleusercontent.com",
          "client_type": 3
        }
      ],
      "api_key": [
        {
          "current_key": "AIzaSyC2TNcVnrdpOTxy1X-C7jhln2SphDUjBq0"
        }
      ],
      "services": {
        "appinvite_service": {
          "other_platform_oauth_client": [
            {
              "client_id": "348147721474-bu0htpm6ricu3d4dlunje7gmfidkdga3.apps.googleusercontent.com",
              "client_type": 3
            }
          ]
        }
      }
    }
  ],
  "configuration_version": "1"
}